AUTHORS.md
CHANGES.md
COPYING
MANIFEST.in
README.api
README.rst
setup.py
src/jottalib/JFS.py
src/jottalib/__init__.py
src/jottalib/cli.py
src/jottalib/jottacloud.py
src/jottalib/jottafuse.py
src/jottalib/monitor.py
src/jottalib/qt.py
src/jottalib/scanner.py
src/jottalib.egg-info/PKG-INFO
src/jottalib.egg-info/SOURCES.txt
src/jottalib.egg-info/dependency_links.txt
src/jottalib.egg-info/entry_points.txt
src/jottalib.egg-info/pbr.json
src/jottalib.egg-info/requires.txt
src/jottalib.egg-info/top_level.txt
src/jottalib/contrib/__init__.py
src/jottalib/contrib/mwt.py
src/jottalib/contrib/readlnk.py